{"cameraMode":{"drawMode":0,"name":"Shaded","section":"Shading Mode"},"sceneLighting":true,"audioPlay":false,"sceneViewState":{"showFog":true,"showMaterialUpdate":false,"showSkybox":true,"showFlares":true,"showImageEffects":true,"showParticleSystems":true},"in2DMode":false,"pivot":{"x":2.6604607105255129,"y":0.8321591019630432,"z":-2.6591811180114748},"rotation":{"x":0.012637904845178128,"y":-0.9172239303588867,"z":0.02918536774814129,"w":0.3971365988254547},"size":1.9698662757873536,"orthographic":false}